chippy_ai/.gitignore
chippy_ai/README.MD
chippy_ai/__init__.py
chippy_ai/config.ini
chippy_ai/main.py
chippy_ai/pyproject.toml
chippy_ai/cheats/git.txt
chippy_ai/cheats/shell.txt
chippy_ai/env/placeholder.txt
chippy_ai-0.2.8.dist-info/METADATA
chippy_ai-0.2.8.dist-info/WHEEL
chippy_ai-0.2.8.dist-info/entry_points.txt
chippy_ai-0.2.8.dist-info/licenses/LICENSE
chippy_ai-0.2.8.dist-info/RECORD
