Metadata-Version: 2.3
Name: chippy_ai
Version: 0.2.8
Summary: A compact CLI for beginners.
Project-URL: Homepage, https://github.com/alexbehrens/chip
Project-URL: Issues, https://github.com/alexbehrens/chip/issues
Author-email: Alex Behrens <alexanderbbehrens@gmail.com>
License-File: LICENSE
Classifier: License :: OSI Approved :: Apache Software License
Classifier: Operating System :: OS Independent
Classifier: Programming Language :: Python :: 3
Requires-Python: >=3.8
Requires-Dist: openai
Requires-Dist: python-dotenv
